typeinc/__init__.py
typeinc/main.py
typeinc/wordlist.txt
typeinc/configurations/input_config.py
typeinc/configurations/keyboard.py
typeinc/configurations/mainscreen.py
typeinc/configurations/result.py
typeinc/configurations/text_gen.py
typeinc/configurations/ui.py
typeinc/scores/highscore.py
typeinc/scores/scores.json
typeinc-1.0.2.dist-info/METADATA
typeinc-1.0.2.dist-info/WHEEL
typeinc-1.0.2.dist-info/entry_points.txt
typeinc-1.0.2.dist-info/licenses/LICENSE.md
typeinc-1.0.2.dist-info/RECORD
