Metadata-Version: 2.4
Name: Typeinc
Version: 1.0.2
Summary: Typeinc, an ncurses based tool, is your goto terminal tool to play around with your typing speed with various difficulty levels.
Author: AnirudhG07
License-File: LICENSE.md
Keywords: CLI,terminal,typing,typing speed test
Classifier: Development Status :: 5 - Production/Stable
Classifier: Intended Audience :: Developers
Classifier: License :: OSI Approved :: Apache Software License
Classifier: Operating System :: MacOS
Classifier: Operating System :: Microsoft :: Windows
Classifier: Operating System :: POSIX
Classifier: Programming Language :: Python :: 3.11
Classifier: Programming Language :: Python :: 3.12
Classifier: Topic :: Games/Entertainment
Requires-Python: >=3.11
Requires-Dist: setuptools>=80.9.0
